jupyterlab_unianalytics_dashboard/__init__.py
jupyterlab_unianalytics_dashboard/_version.py
jupyterlab_unianalytics_dashboard/handlers.py
jupyterlab_unianalytics_dashboard/tests/__init__.py
jupyterlab_unianalytics_dashboard/tests/test_handlers.py
jupyterlab_unianalytics_dashboard-4.0.21.data/data/etc/jupyter/jupyter_server_config.d/jupyterlab_unianalytics_dashboard.json
jupyterlab_unianalytics_dashboard-4.0.21.data/data/share/jupyter/labextensions/jupyterlab_unianalytics_dashboard/package.json
jupyterlab_unianalytics_dashboard-4.0.21.data/data/share/jupyter/labextensions/jupyterlab_unianalytics_dashboard/schemas/jupyterlab_unianalytics_dashboard/endpoint.json
jupyterlab_unianalytics_dashboard-4.0.21.data/data/share/jupyter/labextensions/jupyterlab_unianalytics_dashboard/schemas/jupyterlab_unianalytics_dashboard/package.json.orig
jupyterlab_unianalytics_dashboard-4.0.21.data/data/share/jupyter/labextensions/jupyterlab_unianalytics_dashboard/schemas/jupyterlab_unianalytics_dashboard/plugin.json
jupyterlab_unianalytics_dashboard-4.0.21.data/data/share/jupyter/labextensions/jupyterlab_unianalytics_dashboard/static/10.1e5c908a94fc4b83c2e5.js
jupyterlab_unianalytics_dashboard-4.0.21.data/data/share/jupyter/labextensions/jupyterlab_unianalytics_dashboard/static/18.759fbf2374edc42b5c3e.js
jupyterlab_unianalytics_dashboard-4.0.21.data/data/share/jupyter/labextensions/jupyterlab_unianalytics_dashboard/static/18.759fbf2374edc42b5c3e.js.LICENSE.txt
jupyterlab_unianalytics_dashboard-4.0.21.data/data/share/jupyter/labextensions/jupyterlab_unianalytics_dashboard/static/308.d9da4ce35f354c6f12e1.js
jupyterlab_unianalytics_dashboard-4.0.21.data/data/share/jupyter/labextensions/jupyterlab_unianalytics_dashboard/static/39.5a3b28a79ba693a9b627.js
jupyterlab_unianalytics_dashboard-4.0.21.data/data/share/jupyter/labextensions/jupyterlab_unianalytics_dashboard/static/426.a7015f9dfda310972c1b.js
jupyterlab_unianalytics_dashboard-4.0.21.dist-info/METADATA
jupyterlab_unianalytics_dashboard-4.0.21.dist-info/WHEEL
jupyterlab_unianalytics_dashboard-4.0.21.dist-info/licenses/LICENSE
jupyterlab_unianalytics_dashboard-4.0.21.dist-info/RECORD
