Metadata-Version: 2.4
Name: jupyterlab_unianalytics_dashboard
Version: 4.0.21
Dynamic: Keywords
Summary: A JupyterLab dashboard extension to visualize data from students.
Project-URL: Homepage, https://github.com/chili-epfl/jupyter-analytics-dashboard
Project-URL: Bug Tracker, https://github.com/chili-epfl/jupyter-analytics-dashboard/issues
Project-URL: Repository, https://github.com/chili-epfl/jupyter-analytics-dashboard.git
Author-email: Uni Analytics <unianalytics.jupyterlab@hotmail.com>
License: MIT License
License-File: LICENSE
Classifier: Framework :: Jupyter
Classifier: Framework :: Jupyter :: JupyterLab
Classifier: Framework :: Jupyter :: JupyterLab :: 4
Classifier: Framework :: Jupyter :: JupyterLab :: Extensions
Classifier: Framework :: Jupyter :: JupyterLab :: Extensions :: Prebuilt
Classifier: License :: OSI Approved :: MIT License
Classifier: Programming Language :: Python
Classifier: Programming Language :: Python :: 3
Classifier: Programming Language :: Python :: 3.8
Classifier: Programming Language :: Python :: 3.9
Classifier: Programming Language :: Python :: 3.10
Classifier: Programming Language :: Python :: 3.11
Classifier: Programming Language :: Python :: 3.12
Requires-Python: >=3.8
Requires-Dist: jupyter-server<3,>=1.12
Provides-Extra: test
Requires-Dist: coverage; extra == 'test'
Requires-Dist: pytest; extra == 'test'
Requires-Dist: pytest-asyncio; extra == 'test'
Requires-Dist: pytest-cov; extra == 'test'
Requires-Dist: pytest-jupyter[server]>=0.6.0; extra == 'test'
